MANIFEST.in
README.txt
VERSION.txt
paste_wsgiref_simpleserver.py
setup.cfg
setup.py
paste_wsgiref_simpleserver.egg-info/PKG-INFO
paste_wsgiref_simpleserver.egg-info/SOURCES.txt
paste_wsgiref_simpleserver.egg-info/dependency_links.txt
paste_wsgiref_simpleserver.egg-info/entry_points.txt
paste_wsgiref_simpleserver.egg-info/requires.txt
paste_wsgiref_simpleserver.egg-info/top_level.txt